m3u8_dl/M3u8Downloader.py
m3u8_dl/__init__.py
m3u8_dl/cli.py
m3u8_dl/faker.py
m3u8_dl/myprint.py
m3u8_dl/restore.py
m3u8_dl-0.2.3.dist-info/AUTHORS.rst
m3u8_dl-0.2.3.dist-info/LICENSE
m3u8_dl-0.2.3.dist-info/METADATA
m3u8_dl-0.2.3.dist-info/WHEEL
m3u8_dl-0.2.3.dist-info/entry_points.txt
m3u8_dl-0.2.3.dist-info/top_level.txt
m3u8_dl-0.2.3.dist-info/RECORD
