Metadata-Version: 2.1
Name: m3u8-dl
Version: 0.2.3
Summary: Python downloader for HTTP Live Streaming (HLS), which is m3u8 file 
Home-page: https://github.com/kedpter/m3u8_dl
Author: UNKNOWN
Author-email: 790476448@qq.com
License: MIT license
Keywords: m3u8_dl
Platform: UNKNOWN
Classifier: Development Status :: 2 - Pre-Alpha
Classifier: Intended Audience :: Developers
Classifier: License :: OSI Approved :: MIT License
Classifier: Natural Language :: English
Classifier: Programming Language :: Python :: 2
Classifier: Programming Language :: Python :: 2.7
Classifier: Programming Language :: Python :: 3
Classifier: Programming Language :: Python :: 3.4
Classifier: Programming Language :: Python :: 3.5
Classifier: Programming Language :: Python :: 3.6
Requires-Dist: m3u8 (>=0.3.7)
